Workbook

Sheet UOB Sensitivity
A1: UOB — DCF Sensitivity Analysis
A2: Intrinsic Value per Share: Cost of Equity (Ke) vs Terminal Growth Rate
A4: TABLE: Intrinsic Value / Share — Ke vs Terminal Growth
A5: Ke \ Terminal g | B5: 0.015 | C5: 0.02 | D5: 0.025 | E5: 0.03 | F5: 0.035 | G5: 0.04
A6: 0.0815 | B6: =SUMPRODUCT('UOB DDM Valuation'!$B$8*(1+'UOB DDM Valuation'!$B$20)^{1,2,3,4,5}*'UOB DDM Valuation'!$B$11/(1+$A6)^{1,2,3,4,5})+('UOB DDM Valuation'!$B$8*(1+'UOB DDM Valuation'!$B$20)^5*'UOB DDM Valuation'!$B$11*(1+B$5)/($A6-B$5))/(1+$A6)^5 -> 32.265806 | C6: =SUMPRODUCT('UOB DDM Valuation'!$B$8*(1+'UOB DDM Valuation'!$B$20)^{1,2,3,4,5}*'UOB DDM Valuation'!$B$11/(1+$A6)^{1,2,3,4,5})+('UOB DDM Valuation'!$B$8*(1+'UOB DDM Valuation'!$B$20)^5*'UOB DDM Valuation'!$B$11*(1+C$5)/($A6-C$5))/(1+$A6)^5 -> 34.344782 | D6: =SUMPRODUCT('UOB DDM Valuation'!$B$8*(1+'UOB DDM Valuation'!$B$20)^{1,2,3,4,5}*'UOB DDM Valuation'!$B$11/(1+$A6)^{1,2,3,4,5})+('UOB DDM Valuation'!$B$8*(1+'UOB DDM Valuation'!$B$20)^5*'UOB DDM Valuation'!$B$11*(1+D$5)/($A6-D$5))/(1+$A6)^5 -> 36.791719 | E6: =SUMPRODUCT('UOB DDM Valuation'!$B$8*(1+'UOB DDM Valuation'!$B$20)^{1,2,3,4,5}*'UOB DDM Valuation'!$B$11/(1+$A6)^{1,2,3,4,5})+('UOB DDM Valuation'!$B$8*(1+'UOB DDM Valuation'!$B$20)^5*'UOB DDM Valuation'!$B$11*(1+E$5)/($A6-E$5))/(1+$A6)^5 -> 39.713788 | F6: =SUMPRODUCT('UOB DDM Valuation'!$B$8*(1+'UOB DDM Valuation'!$B$20)^{1,2,3,4,5}*'UOB DDM Valuation'!$B$11/(1+$A6)^{1,2,3,4,5})+('UOB DDM Valuation'!$B$8*(1+'UOB DDM Valuation'!$B$20)^5*'UOB DDM Valuation'!$B$11*(1+F$5)/($A6-F$5))/(1+$A6)^5 -> 43.264259 | G6: =SUMPRODUCT('UOB DDM Valuation'!$B$8*(1+'UOB DDM Valuation'!$B$20)^{1,2,3,4,5}*'UOB DDM Valuation'!$B$11/(1+$A6)^{1,2,3,4,5})+('UOB DDM Valuation'!$B$8*(1+'UOB DDM Valuation'!$B$20)^5*'UOB DDM Valuation'!$B$11*(1+G$5)/($A6-G$5))/(1+$A6)^5 -> 47.670266
A7: 0.0865 | B7: =SUMPRODUCT('UOB DDM Valuation'!$B$8*(1+'UOB DDM Valuation'!$B$20)^{1,2,3,4,5}*'UOB DDM Valuation'!$B$11/(1+$A7)^{1,2,3,4,5})+('UOB DDM Valuation'!$B$8*(1+'UOB DDM Valuation'!$B$20)^5*'UOB DDM Valuation'!$B$11*(1+B$5)/($A7-B$5))/(1+$A7)^5 -> 29.967097 | C7: =SUMPRODUCT('UOB DDM Valuation'!$B$8*(1+'UOB DDM Valuation'!$B$20)^{1,2,3,4,5}*'UOB DDM Valuation'!$B$11/(1+$A7)^{1,2,3,4,5})+('UOB DDM Valuation'!$B$8*(1+'UOB DDM Valuation'!$B$20)^5*'UOB DDM Valuation'!$B$11*(1+C$5)/($A7-C$5))/(1+$A7)^5 -> 31.722616 | D7: =SUMPRODUCT('UOB DDM Valuation'!$B$8*(1+'UOB DDM Valuation'!$B$20)^{1,2,3,4,5}*'UOB DDM Valuation'!$B$11/(1+$A7)^{1,2,3,4,5})+('UOB DDM Valuation'!$B$8*(1+'UOB DDM Valuation'!$B$20)^5*'UOB DDM Valuation'!$B$11*(1+D$5)/($A7-D$5))/(1+$A7)^5 -> 33.763586 | E7: =SUMPRODUCT('UOB DDM Valuation'!$B$8*(1+'UOB DDM Valuation'!$B$20)^{1,2,3,4,5}*'UOB DDM Valuation'!$B$11/(1+$A7)^{1,2,3,4,5})+('UOB DDM Valuation'!$B$8*(1+'UOB DDM Valuation'!$B$20)^5*'UOB DDM Valuation'!$B$11*(1+E$5)/($A7-E$5))/(1+$A7)^5 -> 36.16579 | F7: =SUMPRODUCT('UOB DDM Valuation'!$B$8*(1+'UOB DDM Valuation'!$B$20)^{1,2,3,4,5}*'UOB DDM Valuation'!$B$11/(1+$A7)^{1,2,3,4,5})+('UOB DDM Valuation'!$B$8*(1+'UOB DDM Valuation'!$B$20)^5*'UOB DDM Valuation'!$B$11*(1+F$5)/($A7-F$5))/(1+$A7)^5 -> 39.034441 | G7: =SUMPRODUCT('UOB DDM Valuation'!$B$8*(1+'UOB DDM Valuation'!$B$20)^{1,2,3,4,5}*'UOB DDM Valuation'!$B$11/(1+$A7)^{1,2,3,4,5})+('UOB DDM Valuation'!$B$8*(1+'UOB DDM Valuation'!$B$20)^5*'UOB DDM Valuation'!$B$11*(1+G$5)/($A7-G$5))/(1+$A7)^5 -> 42.520006
A8: 0.0915 | B8: =SUMPRODUCT('UOB DDM Valuation'!$B$8*(1+'UOB DDM Valuation'!$B$20)^{1,2,3,4,5}*'UOB DDM Valuation'!$B$11/(1+$A8)^{1,2,3,4,5})+('UOB DDM Valuation'!$B$8*(1+'UOB DDM Valuation'!$B$20)^5*'UOB DDM Valuation'!$B$11*(1+B$5)/($A8-B$5))/(1+$A8)^5 -> 27.969589 | C8: =SUMPRODUCT('UOB DDM Valuation'!$B$8*(1+'UOB DDM Valuation'!$B$20)^{1,2,3,4,5}*'UOB DDM Valuation'!$B$11/(1+$A8)^{1,2,3,4,5})+('UOB DDM Valuation'!$B$8*(1+'UOB DDM Valuation'!$B$20)^5*'UOB DDM Valuation'!$B$11*(1+C$5)/($A8-C$5))/(1+$A8)^5 -> 29.467858 | D8: =SUMPRODUCT('UOB DDM Valuation'!$B$8*(1+'UOB DDM Valuation'!$B$20)^{1,2,3,4,5}*'UOB DDM Valuation'!$B$11/(1+$A8)^{1,2,3,4,5})+('UOB DDM Valuation'!$B$8*(1+'UOB DDM Valuation'!$B$20)^5*'UOB DDM Valuation'!$B$11*(1+D$5)/($A8-D$5))/(1+$A8)^5 -> 31.191431 | E8: =SUMPRODUCT('UOB DDM Valuation'!$B$8*(1+'UOB DDM Valuation'!$B$20)^{1,2,3,4,5}*'UOB DDM Valuation'!$B$11/(1+$A8)^{1,2,3,4,5})+('UOB DDM Valuation'!$B$8*(1+'UOB DDM Valuation'!$B$20)^5*'UOB DDM Valuation'!$B$11*(1+E$5)/($A8-E$5))/(1+$A8)^5 -> 33.195259 | F8: =SUMPRODUCT('UOB DDM Valuation'!$B$8*(1+'UOB DDM Valuation'!$B$20)^{1,2,3,4,5}*'UOB DDM Valuation'!$B$11/(1+$A8)^{1,2,3,4,5})+('UOB DDM Valuation'!$B$8*(1+'UOB DDM Valuation'!$B$20)^5*'UOB DDM Valuation'!$B$11*(1+F$5)/($A8-F$5))/(1+$A8)^5 -> 35.553748 | G8: =SUMPRODUCT('UOB DDM Valuation'!$B$8*(1+'UOB DDM Valuation'!$B$20)^{1,2,3,4,5}*'UOB DDM Valuation'!$B$11/(1+$A8)^{1,2,3,4,5})+('UOB DDM Valuation'!$B$8*(1+'UOB DDM Valuation'!$B$20)^5*'UOB DDM Valuation'!$B$11*(1+G$5)/($A8-G$5))/(1+$A8)^5 -> 38.370196
A9: 0.0965 | B9: =SUMPRODUCT('UOB DDM Valuation'!$B$8*(1+'UOB DDM Valuation'!$B$20)^{1,2,3,4,5}*'UOB DDM Valuation'!$B$11/(1+$A9)^{1,2,3,4,5})+('UOB DDM Valuation'!$B$8*(1+'UOB DDM Valuation'!$B$20)^5*'UOB DDM Valuation'!$B$11*(1+B$5)/($A9-B$5))/(1+$A9)^5 -> 26.217831 | C9: =SUMPRODUCT('UOB DDM Valuation'!$B$8*(1+'UOB DDM Valuation'!$B$20)^{1,2,3,4,5}*'UOB DDM Valuation'!$B$11/(1+$A9)^{1,2,3,4,5})+('UOB DDM Valuation'!$B$8*(1+'UOB DDM Valuation'!$B$20)^5*'UOB DDM Valuation'!$B$11*(1+C$5)/($A9-C$5))/(1+$A9)^5 -> 27.508452 | D9: =SUMPRODUCT('UOB DDM Valuation'!$B$8*(1+'UOB DDM Valuation'!$B$20)^{1,2,3,4,5}*'UOB DDM Valuation'!$B$11/(1+$A9)^{1,2,3,4,5})+('UOB DDM Valuation'!$B$8*(1+'UOB DDM Valuation'!$B$20)^5*'UOB DDM Valuation'!$B$11*(1+D$5)/($A9-D$5))/(1+$A9)^5 -> 28.979579 | E9: =SUMPRODUCT('UOB DDM Valuation'!$B$8*(1+'UOB DDM Valuation'!$B$20)^{1,2,3,4,5}*'UOB DDM Valuation'!$B$11/(1+$A9)^{1,2,3,4,5})+('UOB DDM Valuation'!$B$8*(1+'UOB DDM Valuation'!$B$20)^5*'UOB DDM Valuation'!$B$11*(1+E$5)/($A9-E$5))/(1+$A9)^5 -> 30.671928 | F9: =SUMPRODUCT('UOB DDM Valuation'!$B$8*(1+'UOB DDM Valuation'!$B$20)^{1,2,3,4,5}*'UOB DDM Valuation'!$B$11/(1+$A9)^{1,2,3,4,5})+('UOB DDM Valuation'!$B$8*(1+'UOB DDM Valuation'!$B$20)^5*'UOB DDM Valuation'!$B$11*(1+F$5)/($A9-F$5))/(1+$A9)^5 -> 32.639457 | G9: =SUMPRODUCT('UOB DDM Valuation'!$B$8*(1+'UOB DDM Valuation'!$B$20)^{1,2,3,4,5}*'UOB DDM Valuation'!$B$11/(1+$A9)^{1,2,3,4,5})+('UOB DDM Valuation'!$B$8*(1+'UOB DDM Valuation'!$B$20)^5*'UOB DDM Valuation'!$B$11*(1+G$5)/($A9-G$5))/(1+$A9)^5 -> 34.95522
A10: 0.1015 | B10: =SUMPRODUCT('UOB DDM Valuation'!$B$8*(1+'UOB DDM Valuation'!$B$20)^{1,2,3,4,5}*'UOB DDM Valuation'!$B$11/(1+$A10)^{1,2,3,4,5})+('UOB DDM Valuation'!$B$8*(1+'UOB DDM Valuation'!$B$20)^5*'UOB DDM Valuation'!$B$11*(1+B$5)/($A10-B$5))/(1+$A10)^5 -> 24.669192 | C10: =SUMPRODUCT('UOB DDM Valuation'!$B$8*(1+'UOB DDM Valuation'!$B$20)^{1,2,3,4,5}*'UOB DDM Valuation'!$B$11/(1+$A10)^{1,2,3,4,5})+('UOB DDM Valuation'!$B$8*(1+'UOB DDM Valuation'!$B$20)^5*'UOB DDM Valuation'!$B$11*(1+C$5)/($A10-C$5))/(1+$A10)^5 -> 25.790024 | D10: =SUMPRODUCT('UOB DDM Valuation'!$B$8*(1+'UOB DDM Valuation'!$B$20)^{1,2,3,4,5}*'UOB DDM Valuation'!$B$11/(1+$A10)^{1,2,3,4,5})+('UOB DDM Valuation'!$B$8*(1+'UOB DDM Valuation'!$B$20)^5*'UOB DDM Valuation'!$B$11*(1+D$5)/($A10-D$5))/(1+$A10)^5 -> 27.05737 | E10: =SUMPRODUCT('UOB DDM Valuation'!$B$8*(1+'UOB DDM Valuation'!$B$20)^{1,2,3,4,5}*'UOB DDM Valuation'!$B$11/(1+$A10)^{1,2,3,4,5})+('UOB DDM Valuation'!$B$8*(1+'UOB DDM Valuation'!$B$20)^5*'UOB DDM Valuation'!$B$11*(1+E$5)/($A10-E$5))/(1+$A10)^5 -> 28.501968 | F10: =SUMPRODUCT('UOB DDM Valuation'!$B$8*(1+'UOB DDM Valuation'!$B$20)^{1,2,3,4,5}*'UOB DDM Valuation'!$B$11/(1+$A10)^{1,2,3,4,5})+('UOB DDM Valuation'!$B$8*(1+'UOB DDM Valuation'!$B$20)^5*'UOB DDM Valuation'!$B$11*(1+F$5)/($A10-F$5))/(1+$A10)^5 -> 30.163798 | G10: =SUMPRODUCT('UOB DDM Valuation'!$B$8*(1+'UOB DDM Valuation'!$B$20)^{1,2,3,4,5}*'UOB DDM Valuation'!$B$11/(1+$A10)^{1,2,3,4,5})+('UOB DDM Valuation'!$B$8*(1+'UOB DDM Valuation'!$B$20)^5*'UOB DDM Valuation'!$B$11*(1+G$5)/($A10-G$5))/(1+$A10)^5 -> 32.095844
A11: 0.1065 | B11: =SUMPRODUCT('UOB DDM Valuation'!$B$8*(1+'UOB DDM Valuation'!$B$20)^{1,2,3,4,5}*'UOB DDM Valuation'!$B$11/(1+$A11)^{1,2,3,4,5})+('UOB DDM Valuation'!$B$8*(1+'UOB DDM Valuation'!$B$20)^5*'UOB DDM Valuation'!$B$11*(1+B$5)/($A11-B$5))/(1+$A11)^5 -> 23.290362 | C11: =SUMPRODUCT('UOB DDM Valuation'!$B$8*(1+'UOB DDM Valuation'!$B$20)^{1,2,3,4,5}*'UOB DDM Valuation'!$B$11/(1+$A11)^{1,2,3,4,5})+('UOB DDM Valuation'!$B$8*(1+'UOB DDM Valuation'!$B$20)^5*'UOB DDM Valuation'!$B$11*(1+C$5)/($A11-C$5))/(1+$A11)^5 -> 24.270776 | D11: =SUMPRODUCT('UOB DDM Valuation'!$B$8*(1+'UOB DDM Valuation'!$B$20)^{1,2,3,4,5}*'UOB DDM Valuation'!$B$11/(1+$A11)^{1,2,3,4,5})+('UOB DDM Valuation'!$B$8*(1+'UOB DDM Valuation'!$B$20)^5*'UOB DDM Valuation'!$B$11*(1+D$5)/($A11-D$5))/(1+$A11)^5 -> 25.371486 | E11: =SUMPRODUCT('UOB DDM Valuation'!$B$8*(1+'UOB DDM Valuation'!$B$20)^{1,2,3,4,5}*'UOB DDM Valuation'!$B$11/(1+$A11)^{1,2,3,4,5})+('UOB DDM Valuation'!$B$8*(1+'UOB DDM Valuation'!$B$20)^5*'UOB DDM Valuation'!$B$11*(1+E$5)/($A11-E$5))/(1+$A11)^5 -> 26.616079 | F11: =SUMPRODUCT('UOB DDM Valuation'!$B$8*(1+'UOB DDM Valuation'!$B$20)^{1,2,3,4,5}*'UOB DDM Valuation'!$B$11/(1+$A11)^{1,2,3,4,5})+('UOB DDM Valuation'!$B$8*(1+'UOB DDM Valuation'!$B$20)^5*'UOB DDM Valuation'!$B$11*(1+F$5)/($A11-F$5))/(1+$A11)^5 -> 28.034742 | G11: =SUMPRODUCT('UOB DDM Valuation'!$B$8*(1+'UOB DDM Valuation'!$B$20)^{1,2,3,4,5}*'UOB DDM Valuation'!$B$11/(1+$A11)^{1,2,3,4,5})+('UOB DDM Valuation'!$B$8*(1+'UOB DDM Valuation'!$B$20)^5*'UOB DDM Valuation'!$B$11*(1+G$5)/($A11-G$5))/(1+$A11)^5 -> 29.666737
A12: 0.1115 | B12: =SUMPRODUCT('UOB DDM Valuation'!$B$8*(1+'UOB DDM Valuation'!$B$20)^{1,2,3,4,5}*'UOB DDM Valuation'!$B$11/(1+$A12)^{1,2,3,4,5})+('UOB DDM Valuation'!$B$8*(1+'UOB DDM Valuation'!$B$20)^5*'UOB DDM Valuation'!$B$11*(1+B$5)/($A12-B$5))/(1+$A12)^5 -> 22.054932 | C12: =SUMPRODUCT('UOB DDM Valuation'!$B$8*(1+'UOB DDM Valuation'!$B$20)^{1,2,3,4,5}*'UOB DDM Valuation'!$B$11/(1+$A12)^{1,2,3,4,5})+('UOB DDM Valuation'!$B$8*(1+'UOB DDM Valuation'!$B$20)^5*'UOB DDM Valuation'!$B$11*(1+C$5)/($A12-C$5))/(1+$A12)^5 -> 22.918042 | D12: =SUMPRODUCT('UOB DDM Valuation'!$B$8*(1+'UOB DDM Valuation'!$B$20)^{1,2,3,4,5}*'UOB DDM Valuation'!$B$11/(1+$A12)^{1,2,3,4,5})+('UOB DDM Valuation'!$B$8*(1+'UOB DDM Valuation'!$B$20)^5*'UOB DDM Valuation'!$B$11*(1+D$5)/($A12-D$5))/(1+$A12)^5 -> 23.880933 | E12: =SUMPRODUCT('UOB DDM Valuation'!$B$8*(1+'UOB DDM Valuation'!$B$20)^{1,2,3,4,5}*'UOB DDM Valuation'!$B$11/(1+$A12)^{1,2,3,4,5})+('UOB DDM Valuation'!$B$8*(1+'UOB DDM Valuation'!$B$20)^5*'UOB DDM Valuation'!$B$11*(1+E$5)/($A12-E$5))/(1+$A12)^5 -> 24.96197 | F12: =SUMPRODUCT('UOB DDM Valuation'!$B$8*(1+'UOB DDM Valuation'!$B$20)^{1,2,3,4,5}*'UOB DDM Valuation'!$B$11/(1+$A12)^{1,2,3,4,5})+('UOB DDM Valuation'!$B$8*(1+'UOB DDM Valuation'!$B$20)^5*'UOB DDM Valuation'!$B$11*(1+F$5)/($A12-F$5))/(1+$A12)^5 -> 26.18432 | G12: =SUMPRODUCT('UOB DDM Valuation'!$B$8*(1+'UOB DDM Valuation'!$B$20)^{1,2,3,4,5}*'UOB DDM Valuation'!$B$11/(1+$A12)^{1,2,3,4,5})+('UOB DDM Valuation'!$B$8*(1+'UOB DDM Valuation'!$B$20)^5*'UOB DDM Valuation'!$B$11*(1+G$5)/($A12-G$5))/(1+$A12)^5 -> 27.577627
A14: Current share price for reference: | B14: ='UOB DDM Valuation'!$B$6 -> 36.65
